xurpas_data_quality/__init__.py
xurpas_data_quality/config.py
xurpas_data_quality/data_report.py
xurpas_data_quality/data/__init__.py
xurpas_data_quality/data/compare.py
xurpas_data_quality/data/correlations.py
xurpas_data_quality/data/dataframe.py
xurpas_data_quality/data/describe.py
xurpas_data_quality/data/describer.py
xurpas_data_quality/data/descriptions.py
xurpas_data_quality/data/series_describe.py
xurpas_data_quality/data/typeset.py
xurpas_data_quality/data/utils.py
xurpas_data_quality/data/alerts/__init__.py
xurpas_data_quality/data/alerts/alerts.py
xurpas_data_quality/data/algorithms/__init__.py
xurpas_data_quality/data/algorithms/summary_algorithms.py
xurpas_data_quality/data/type_descriptions/__init__.py
xurpas_data_quality/data/type_descriptions/describe_categorical.py
xurpas_data_quality/data/type_descriptions/describe_date.py
xurpas_data_quality/data/type_descriptions/describe_generic.py
xurpas_data_quality/data/type_descriptions/describe_numeric.py
xurpas_data_quality/data/type_descriptions/describe_string.py
xurpas_data_quality/render/__init__.py
xurpas_data_quality/render/handler.py
xurpas_data_quality/render/render.py
xurpas_data_quality/render/render_compare.py
xurpas_data_quality/render/render_empty.py
xurpas_data_quality/render/render_error.py
xurpas_data_quality/render/render_sections.py
xurpas_data_quality/render/render_test.py
xurpas_data_quality/render/renderer.py
xurpas_data_quality/render/template_loader.py
xurpas_data_quality/render/render_types/__init__.py
xurpas_data_quality/render/render_types/render_categorical.py
xurpas_data_quality/render/render_types/render_date.py
xurpas_data_quality/render/render_types/render_generic.py
xurpas_data_quality/render/render_types/render_numerical.py
xurpas_data_quality/render/render_types/render_string.py
xurpas_data_quality/render/render_types/bottom/__init__.py
xurpas_data_quality/render/render_types/bottom/render_bottom_categorical.py
xurpas_data_quality-1.7.1.dist-info/METADATA
xurpas_data_quality-1.7.1.dist-info/WHEEL
xurpas_data_quality-1.7.1.dist-info/top_level.txt
xurpas_data_quality-1.7.1.dist-info/RECORD
