Metadata-Version: 2.4
Name: xurpas_data_quality
Version: 1.7.1
Summary: XAIL Data quality
Author: Neil Ortaliz
Author-email: Neil Ortaliz <neil.ortaliz@xurpas.com>
License: MIT License
Classifier: Development Status :: 3 - Alpha
Classifier: Intended Audience :: Developers
Classifier: Natural Language :: English
Classifier: Programming Language :: Python :: 3
Requires-Python: >=3.10
Requires-Dist: visions
Requires-Dist: matplotlib
Requires-Dist: pandas
Requires-Dist: numpy<2.2,>=1.24
Requires-Dist: jinja2
Requires-Dist: openpyxl
Requires-Dist: pyarrow
Requires-Dist: pytest
Requires-Dist: minify_html
Requires-Dist: wordcloud
Requires-Dist: pydantic-settings
Requires-Dist: pyspark
Requires-Dist: pyyaml
Requires-Dist: soupsieve
Requires-Dist: polars[pandas]
Requires-Dist: pypdfium2
Requires-Dist: xlsxwriter
Requires-Dist: llvmlite
Requires-Dist: imagehash
Dynamic: author
